<?xml version="1.0" encoding="UTF-8"?>


  <PreservedValue comments="GasConfig">
    <Param name="GasLeakRate" dataObject="/SETUP/PreservedValue/GasLeakRate" type="D" min="-1" max="1000" units="mTorr/Min" accuracy="0.0001" default="0" />
    <Param name="GasLeakRateDate" dataObject="/SETUP/PreservedValue/GasLeakRateDate" type="S" maxLength="50" default="" />
    <Param name="ChamberLeakRate" dataObject="/SETUP/PreservedValue/ChamberLeakRate" type="D" min="0" max="1000" units="mTorr/Min" accuracy="0.0001" default="0" />
    <Param name="ChamberLeakRateDate" dataObject="/SETUP/PreservedValue/ChamberLeakRateDate" type="S" maxLength="50" default="" />
    <Param name="BasePressure" dataObject="/SETUP/PreservedValue/BasePressure" type="D" min="0" max="1000" units="mTorr" accuracy="0.0001" default="0" />
    <Param name="BasePressureDate" dataObject="/SETUP/PreservedValue/BasePressureDate" type="S" maxLength="50" default="" />
    <Param name="MaxProcessTimeTolerance" dataObject="/SETUP/PreservedValue/MaxProcessTimeTolerance" type="D" min="5" max="1000" units="s" accuracy="0.1" default="100" />
    <Param name="LFMaxSetPowerLimit" dataObject="/SETUP/PreservedValue/LFMaxSetPowerLimit" type="D" min="0" max="1500" units="s" accuracy="0.1" default="600" />
    <Param name="ESCTempAutoSet" dataObject="/SETUP/PreservedValue/ESCTempAutoSet" type="I" min="0" max="1" descriptorList="False:0,True:1" units="" default="False" />
    <Param name="SRCPiecewiseSetpointData" dataObject="/SETUP/PreservedValue/SRCGeneratorPiecewiseSetpointDate" type="S" maxLength="10000" default="" />
    <Param name="SRCPiecewiseMeterData" dataObject="/SETUP/PreservedValue/SRCGeneratorPiecewiseMeterData" type="S" maxLength="10000" default="" />
    <Param name="SRCPiecewiseKCoefficient" dataObject="/SETUP/PreservedValue/SRCGeneratorPiecewiseKCoefficient" type="S" maxLength="10000" default="" />
    <Param name="SRCPiecewiseBCoefficient" dataObject="/SETUP/PreservedValue/SRCGeneratorPiecewiseBCoefficient" type="S" maxLength="10000" default="" />
    <Param name="LFPiecewiseSetpointData" dataObject="/SETUP/PreservedValue/LFGeneratorPiecewiseSetpointDate" type="S" maxLength="10000" default="" />
    <Param name="LFPiecewiseMeterData" dataObject="/SETUP/PreservedValue/LFGeneratorPiecewiseMeterData" type="S" maxLength="10000" default="" />
    <Param name="LFPiecewiseKCoefficient" dataObject="/SETUP/PreservedValue/LFGeneratorPiecewiseKCoefficient" type="S" maxLength="10000" default="" />
    <Param name="LFPiecewiseBCoefficient" dataObject="/SETUP/PreservedValue/LFGeneratorPiecewiseBCoefficient" type="S" maxLength="10000" default="" />
    <Option index="1">
      <Value paramName="GasLeakRate">0.1881</Value>
      <Value paramName="GasLeakRateDate">2024-11-02 23:32:11.502</Value>
      <Value paramName="ChamberLeakRate">2.8572</Value>
      <Value paramName="ChamberLeakRateDate">2024-11-11 10:51:08.822</Value>
      <Value paramName="BasePressure">0.2</Value>
      <Value paramName="BasePressureDate">2024-09-23 09:37:59.486</Value>
      <Value paramName="MaxProcessTimeTolerance">1000</Value>
      <Value paramName="LFMaxSetPowerLimit">1500</Value>
      <Value paramName="ESCTempAutoSet">False</Value>
      <Value paramName="SRCPiecewiseSetpointData">0;400;500;600;700;800;900;1000;1200;1400;1600;1800;2000;2200;2400;2600;2800;3000;6000</Value>
      <Value paramName="SRCPiecewiseMeterData">0;383;480;577;673;769;866;963;1156;1348;1542;1734;1927;2120;2313;2508;2701;2899;6000</Value>
      <Value paramName="SRCPiecewiseKCoefficient">0.958;0.97;0.97;0.96;0.96;0.97;0.97;0.965;0.96;0.97;0.96;0.965;0.965;0.965;0.975;0.965;0.99;1.034</Value>
      <Value paramName="SRCPiecewiseBCoefficient">0;-5;-5;1;1;-7;-7;-2;4;-10;6;-3;-3;-3;-27;-1;-71;-202</Value>
      <Value paramName="LFPiecewiseSetpointData">0;20;50;80;100;200;300;400;500;600;700;800;900;1000;1100;1200;1300;1400;1500</Value>
      <Value paramName="LFPiecewiseMeterData">0;20.8;50.7;80.9;101.1;202;303.1;403.9;505;606.2;707.2;808.1;908.3;1010;1111.1;1215.2;1315.8;1417.8;1500</Value>
      <Value paramName="LFPiecewiseKCoefficient">1.04;0.997;1.007;1.01;1.009;1.011;1.008;1.011;1.012;1.01;1.009;1.002;1.017;1.011;1.041;1.006;1.02;0.822</Value>
      <Value paramName="LFPiecewiseBCoefficient">0;0.867;0.367;0.1;0.2;-0.2;0.7;-0.5;-1;0.2;0.9;6.5;-7;-1;-34;8;-10.2;267</Value>
    </Option>
  </PreservedValue>

